Workbook

Sheet Respuestas
A1: Columna 1 | B1: clave_acceso | C1: tipo_propiedad | D1: ubicacion | E1: tipo_ciudad (A/B/C/D) | F1: arquetipo (CHT/CBD/FRA/CMS/CLI/PRN) | G1: zona (opcional) | H1: valor_mercado_hoy_MXN | I1: horizonte_meses | J1: planea_construir (Si/No) | K1: m2_construccion | L1: costo_m2_MXN | M1: meses_obra | N1: destino_post (Rentar/Vender/No se) | O1: renta_post_MXN | P1: precio_venta_post_MXN | Q1: costos_post_MXN | R1: renta_mensual_actual_MXN | S1: ocupacion_esperada_(0-1_o_% ) | T1: gasto_mensual_propiedad_MXN | U1: meses_para_vender_hoy | V1: pct_costos_venta (ej. 6%) | W1: risk_legal | X1: risk_servicios | Y1: risk_mercado | Z1: risk_seguridad | AA1: risk_accesos | AB1: risk_fisicos | AC1: risk_condominio | AD1: risk_obra_publica | AE1: risk_competencia | AF1: nombre | AG1: email | AH1: whatsapp | AI1: Acepto la nota: Entiendo que este resultado no es asesoría personalizada y depende de mis datos y del mercado.
A2: 45908.664 | B2: VALOROCULTO | C2: Terreno | D2: CENTRO/ CUAUTITLAN / EDO MEX | E2: C | F2: CMS | G2: Periférica | H2: 2000000 | I2: 36 | J2: Si | K2: 200 | M2: 9+ | N2: No se | R2: 50000 | T2: 3500 | U2: 5 | V2: 0.07 | W2: Si | X2: No | Y2: No | Z2: Si | AB2: No | AC2: No | AE2: Si | AF2: ERNESTO OROZCO | AG2: ernestoorozcosolares@gmail.com | AH2: +5215655693975
A3: 45908.679 | B3: VALOROCULTO | C3: Casa | D3: CENTRO CUAUTITLÁN ESTADO DE MEXICO | E3: C | F3: PRN | G3: No sé | H3: 2000000 | I3: 24 | J3: Si | K3: 350 | L3: 11 | M3: 9+ | N3: Vender | O3: 35800 | U3: 7+ | V3: 0.08 | W3: Si | X3: No | Y3: Si | Z3: Si | AA3: Si | AB3: Si | AC3: No | AD3: No | AE3: Si | AF3: ERNESTO OROZCO | AG3: ernestoorozcosolares@gmail.com | AH3: +5215655693975 | AI3: acepto
A4: 45908.699 | B4: VALOROCULTO | C4: Casa | D4: CENTRO DE CUAUTITLAN ESTADO DE MEXICO | E4: B | F4: CBD | G4: Periférica | H4: 2200000 | I4: 36 | J4: Si | K4: 200 | L4: 12000 | M4: 9+ | N4: No se | P4: 2500000 | Q4: 5000 | R4: 18000 | U4: 7+ | V4: No se | W4: Si | X4: Si | Y4: Si | Z4: No | AA4: Si | AB4: No | AC4: Si | AD4: No | AE4: Si | AF4: ernesto Orozco | AG4: ernestoorozcosolares@gmail.com | AH4: +5215655693975 | AI4: acepto
A5: 45909.468 | B5: VALOROCULTO | C5: Departamento | D5: CENTRO CUAUTITLAN ESTADO DE MEXICO | E5: B | F5: CBD | G5: Intermedia | H5: 4000000 | I5: 24 | J5: Si | K5: 350 | L5: 15000 | M5: 9+ | N5: Vender | O5: 35000 | P5: 4.5 | Q5: 5600 | R5: 35000 | S5: 0.5 | T5: $3,500.00 | U5: 7+ | V5: 0.05 | W5: Si | X5: Si | Y5: No | Z5: Si | AA5: Si | AB5: Si | AC5: No | AD5: No | AE5: Si | AF5: ERNESTO SOLARES | AG5: e@o.com.mx | AH5: +5215655693975 | AI5: acepto

Sheet Respuestas (old)
A1: Respuestas del Form (una fila por cliente)
A3: timestamp | B3: clave_acceso | C3: tipo_propiedad | D3: ubicacion | E3: tipo_ciudad (A/B/C/D) | F3: arquetipo (CHT/CBD/FRA/CMS/CLI/PRN) | G3: zona (opcional) | H3: valor_mercado_hoy_MXN | I3: horizonte_meses | J3: planea_construir (Si/No) | K3: m2_construccion | L3: costo_m2_MXN | M3: meses_obra | N3: destino_post (Rentar/Vender/No se) | O3: renta_post_MXN | P3: precio_venta_post_MXN | Q3: costos_post_MXN | R3: renta_mensual_actual_MXN | S3: ocupacion_esperada_(0-1_o_% ) | T3: gasto_mensual_propiedad_MXN | U3: meses_para_vender_hoy | V3: pct_costos_venta (ej. 6%) | W3: risk_legal | X3: risk_servicios | Y3: risk_mercado | Z3: risk_seguridad | AA3: risk_accesos | AB3: risk_fisicos | AC3: risk_condominio | AD3: risk_obra_publica | AE3: risk_competencia | AF3: nombre | AG3: email | AH3: whatsapp
A5: Nota: | B5: Si en tu Form usas una sola pregunta con casillas múltiples para riesgos, conviértelas a 0/1 en estas columnas con n8n.

Sheet Base_TipoCiudad
A1: Valores prudentes base por Tipo de ciudad (A/B/C/D)
A3: Variable_key | B3: Unidad/nota | C3: A Metrópoli top | D3: B Capital/Regional | E3: C Mediana/Satélite | F3: D Local/Periférica
A4: meses_vender | B4: meses | C4: 3 | D4: 4 | E4: 5 | F4: 6
A5: ocupacion_hoy | B5: 0–1 | C5: 0.93 | D5: 0.9 | E5: 0.87 | F5: 0.85
A6: gasto_mensual_pct_valor | B6: % del valor/mes | C6: 0.001 | D6: 0.0008 | E6: 0.0007 | F6: 0.0006
A7: costos_venta_pct | B7: % del precio venta | C7: 0.06 | D7: 0.06 | E7: 0.06 | F7: 0.065
A8: tasa_descuento_anual | B8: % anual | C8: 0.16 | D8: 0.18 | E8: 0.19 | F8: 0.2
A9: plusvalia_anual | B9: % anual | C9: 0.06 | D9: 0.05 | E9: 0.045 | F9: 0.04
A10: horizonte_meses | B10: meses (default si vacío) | C10: 24 | D10: 24 | E10: 24 | F10: 30
A11: costo_m2 | B11: MXN/m² (obra sencilla) | C11: 15000 | D11: 12000 | E11: 11000 | F11: 10000
A12: meses_obra | B12: meses | C12: 6 | D12: 7 | E12: 7 | F12: 8
A13: permisos_otros_mxn | B13: MXN (licencias, conexiones, imprev.) | C13: 100000 | D13: 80000 | E13: 75000 | F13: 70000
A14: ocupacion_post | B14: 0–1 | C14: 0.93 | D14: 0.9 | E14: 0.88 | F14: 0.86
A15: renta_post_pct_valor_post | B15: % del valor post-obra/mes | C15: 0.009 | D15: 0.0075 | E15: 0.007 | F15: 0.006
A16: costos_post_pct_valor_post | B16: % del valor post-obra/mes | C16: 0.0012 | D16: 0.001 | E16: 0.0009 | F16: 0.0008

Sheet Arquetipos_Deltas
A1: Ajustes por Arquetipo (Δ sobre la base del Tipo de ciudad)
A3: Arquetipo | B3: Descripción breve | C3: Δ_meses_vender | D3: Δ_ocupacion_hoy | E3: Δ_gasto_mensual_pct_valor | F3: Δ_costos_venta_pct | G3: Δ_tasa_descuento_anual | H3: Δ_plusvalia_anual | I3: Δ_horizonte_meses | J3: Δ_costo_m2 | K3: Δ_meses_obra | L3: Δ_permisos_otros_mxn | M3: Δ_ocupacion_post | N3: Δ_renta_post_pct_valor_post | O3: Δ_costos_post_pct_valor_post
A4: CHT | B4: Centro histórico/tradicional (denso, mixto, restaurado) | C4: -1 | D4: 0.02 | E4: 0 | F4: 0 | G4: -0.01 | H4: 0.005 | I4: 0 | J4: 1500 | K4: 0 | L4: 20000 | M4: 0 | N4: 0.001 | O4: 0
A5: CBD | B5: Corredor de negocios/servicios (prime, obra mixta) | C5: -1 | D5: 0.02 | E5: 0 | F5: 0 | G5: -0.02 | H5: 0.01 | I5: 1 | J5: 3000 | K5: 1 | L5: 30000 | M5: 0 | N5: 0.0015 | O5: 0.0003
A6: FRA | B6: Residencial 1er anillo alto (anclas, ingresos altos) | C6: -1 | D6: 0.02 | E6: 0 | F6: 0 | G6: -0.01 | H6: 0.005 | I6: 0 | J6: 2000 | K6: 0 | L6: 0 | M6: 0 | N6: 0.001 | O6: 0.0002
A7: CMS | B7: Centro municipal secundario (demanda local) | C7: 0 | D7: 0 | E7: 0 | F7: 0 | G7: 0 | H7: 0 | I7: 0 | J7: 0 | K7: 0 | L7: 0 | M7: 0 | N7: 0 | O7: 0
A8: CLI | B8: Corredor logístico/industrial (servicios a parque) | C8: 1 | D8: 0.01 | E8: 0 | F8: 0 | G8: 0.01 | H8: 0 | I8: 0 | J8: -1000 | K8: 0 | L8: 0 | M8: 0 | N8: -0.001 | O8: 0
A9: PRN | B9: Periferia residencial nueva (servicios en desarrollo) | C9: 1 | D9: -0.05 | E9: 0 | F9: 0 | G9: 0.02 | H9: -0.01 | I9: 1 | J9: -1000 | K9: 1 | L9: 0 | M9: 0 | N9: -0.001 | O9: 0

Sheet Arquetipos_Info
A1: Arquetipos (ícono + descripción)
A3: Arquetipo | B3: Ícono | C3: Descripción
A4: CHT | B4: 🏛️ | C4: Núcleo histórico/mixto, alto flujo peatonal; posibles restricciones patrimoniales.
A5: CBD | B5: 🏙️ | C5: Corredor de oficinas/servicios prime; obra y costos más altos.
A6: FRA | B6: 🏡 | C6: Residencial consolidado de 1er anillo con anclas y poder adquisitivo.
A7: CMS | B7: 🧭 | C7: Centro municipal activo con demanda local y valores intermedios.
A8: CLI | B8: 🏭 | C8: Zona logística/industrial; servicios para parques y empleo.
A9: PRN | B9: 🧱 | C9: Periferia en expansión; fricción mayor y servicios en desarrollo.

Sheet Semaforo_Pesos
A1: Pesos del Semáforo de riesgo (suma 1.00)
A3: Señal | B3: Peso
A4: risk_legal | B4: 0.25
A5: risk_servicios | B5: 0.15
A6: risk_mercado | B6: 0.15
A7: risk_seguridad | B7: 0.1
A8: risk_accesos | B8: 0.1
A9: risk_fisicos | B9: 0.1
A10: risk_condominio | B10: 0.05
A11: risk_obra_publica | B11: 0.05
A12: risk_competencia | B12: 0.05

Sheet Defaults_por_respuesta
A1: Defaults combinados por Tipo de ciudad + Arquetipo (fila 2 de Respuestas)
A3: Tipo de ciudad | B3: {=INDEX(Respuestas!2:2, MATCH("tipo_ciudad (A/B/C/D)", Respuestas!1:1, 0))} -> C
A4: Arquetipo | B4: {=INDEX(Respuestas!2:2, MATCH("arquetipo (CHT/CBD/FRA/CMS/CLI/PRN)", Respuestas!1:1, 0))} -> CMS
A5: Valor mercado hoy (MXN) | B5: {=INDEX(Respuestas!2:2, MATCH("valor_mercado_hoy_MXN", Respuestas!1:1, 0))} -> 2000000
A7: Variable_key | B7: Unidad/nota | C7: Base (Tipo) | D7: Δ (Arquetipo) | E7: Resultado Default | F7: Override (Respuestas) | G7: Usado
A8: meses_vender | B8: meses | C8: {=IF($B$3="A", INDEX(Base_TipoCiudad!C:C, MATCH(A8, Base_TipoCiudad!A:A, 0)), IF($B$3="B", INDEX(Base_TipoCiudad!D:D, MATCH(A8, Base_TipoCiudad!A:A, 0)), IF($B$3="C", INDEX(Base_TipoCiudad!E:E, MATCH(A8, Base_TipoCiudad!A:A, 0)), INDEX(Base_TipoCiudad!F:F, MATCH(A8, Base_TipoCiudad!A:A, 0)))))} -> 5 | D8: {=INDEX(Arquetipos_Deltas!$C:$O, MATCH($B$4, Arquetipos_Deltas!$A:$A, 0), MATCH("Δ_"&A8, Arquetipos_Deltas!$C$3:$O$3, 0))} -> 0 | E8: =C8+D8 -> 5 | F8: {=IFERROR(VALUE(SUBSTITUTE(INDEX(Respuestas!2:2, MATCH("meses_para_vender_hoy", Respuestas!1:1, 0)), "+", "")), "")} -> 5 | G8: =IF(B8="0–1", MAX(0, MIN(1, IF(F8="", E8, F8))), IF(ISNUMBER(SEARCH("meses", B8)), MAX(0, IF(F8="", E8, F8)), IF(F8="", E8, F8))) -> 5
A9: ocupacion_hoy | B9: 0–1 | C9: {=IF($B$3="A", INDEX(Base_TipoCiudad!C:C, MATCH(A9, Base_TipoCiudad!A:A, 0)), IF($B$3="B", INDEX(Base_TipoCiudad!D:D, MATCH(A9, Base_TipoCiudad!A:A, 0)), IF($B$3="C", INDEX(Base_TipoCiudad!E:E, MATCH(A9, Base_TipoCiudad!A:A, 0)), INDEX(Base_TipoCiudad!F:F, MATCH(A9, Base_TipoCiudad!A:A, 0)))))} -> 0.87 | D9: {=INDEX(Arquetipos_Deltas!$C:$O, MATCH($B$4, Arquetipos_Deltas!$A:$A, 0), MATCH("Δ_"&A9, Arquetipos_Deltas!$C$3:$O$3, 0))} -> 0 | E9: =C9+D9 -> 0.87 | G9: =IF(B9="0–1", MAX(0, MIN(1, IF(F9="", E9, F9))), IF(ISNUMBER(SEARCH("meses", B9)), MAX(0, IF(F9="", E9, F9)), IF(F9="", E9, F9))) -> 0.87
A10: gasto_mensual_pct_valor | B10: % del valor/mes | C10: {=IF($B$3="A", INDEX(Base_TipoCiudad!C:C, MATCH(A10, Base_TipoCiudad!A:A, 0)), IF($B$3="B", INDEX(Base_TipoCiudad!D:D, MATCH(A10, Base_TipoCiudad!A:A, 0)), IF($B$3="C", INDEX(Base_TipoCiudad!E:E, MATCH(A10, Base_TipoCiudad!A:A, 0)), INDEX(Base_TipoCiudad!F:F, MATCH(A10, Base_TipoCiudad!A:A, 0)))))} -> 0.0007 | D10: {=INDEX(Arquetipos_Deltas!$C:$O, MATCH($B$4, Arquetipos_Deltas!$A:$A, 0), MATCH("Δ_"&A10, Arquetipos_Deltas!$C$3:$O$3, 0))} -> 0 | E10: =C10+D10 -> 0.0007 | G10: =IF(B10="0–1", MAX(0, MIN(1, IF(F10="", E10, F10))), IF(ISNUMBER(SEARCH("meses", B10)), MAX(0, IF(F10="", E10, F10)), IF(F10="", E10, F10))) -> 0.0007
A11: costos_venta_pct | B11: % del precio venta | C11: {=IF($B$3="A", INDEX(Base_TipoCiudad!C:C, MATCH(A11, Base_TipoCiudad!A:A, 0)), IF($B$3="B", INDEX(Base_TipoCiudad!D:D, MATCH(A11, Base_TipoCiudad!A:A, 0)), IF($B$3="C", INDEX(Base_TipoCiudad!E:E, MATCH(A11, Base_TipoCiudad!A:A, 0)), INDEX(Base_TipoCiudad!F:F, MATCH(A11, Base_TipoCiudad!A:A, 0)))))} -> 0.06 | D11: {=INDEX(Arquetipos_Deltas!$C:$O, MATCH($B$4, Arquetipos_Deltas!$A:$A, 0), MATCH("Δ_"&A11, Arquetipos_Deltas!$C$3:$O$3, 0))} -> 0 | E11: =C11+D11 -> 0.06 | F11: {=IF(OR(ISBLANK(INDEX(Respuestas!2:2, MATCH("pct_costos_venta (ej. 6%)", Respuestas!1:1, 0))), INDEX(Respuestas!2:2, MATCH("pct_costos_venta (ej. 6%)", Respuestas!1:1, 0))="No se", INDEX(Respuestas!2:2, MATCH("pct_costos_venta (ej. 6%)", Respuestas!1:1, 0))="No sé"), "", VALUE(SUBSTITUTE(INDEX(Respuestas!2:2, MATCH("pct_costos_venta (ej. 6%)", Respuestas!1:1, 0)), "%", ""))/100)} -> 0.07 | G11: =IF(B11="0–1", MAX(0, MIN(1, IF(F11="", E11, F11))), IF(ISNUMBER(SEARCH("meses", B11)), MAX(0, IF(F11="", E11, F11)), IF(F11="", E11, F11))) -> 0.07
A12: tasa_descuento_anual | B12: % anual | C12: {=IF($B$3="A", INDEX(Base_TipoCiudad!C:C, MATCH(A12, Base_TipoCiudad!A:A, 0)), IF($B$3="B", INDEX(Base_TipoCiudad!D:D, MATCH(A12, Base_TipoCiudad!A:A, 0)), IF($B$3="C", INDEX(Base_TipoCiudad!E:E, MATCH(A12, Base_TipoCiudad!A:A, 0)), INDEX(Base_TipoCiudad!F:F, MATCH(A12, Base_TipoCiudad!A:A, 0)))))} -> 0.19 | D12: {=INDEX(Arquetipos_Deltas!$C:$O, MATCH($B$4, Arquetipos_Deltas!$A:$A, 0), MATCH("Δ_"&A12, Arquetipos_Deltas!$C$3:$O$3, 0))} -> 0 | E12: =C12+D12 -> 0.19 | G12: =IF(B12="0–1", MAX(0, MIN(1, IF(F12="", E12, F12))), IF(ISNUMBER(SEARCH("meses", B12)), MAX(0, IF(F12="", E12, F12)), IF(F12="", E12, F12))) -> 0.19
A13: plusvalia_anual | B13: % anual | C13: {=IF($B$3="A", INDEX(Base_TipoCiudad!C:C, MATCH(A13, Base_TipoCiudad!A:A, 0)), IF($B$3="B", INDEX(Base_TipoCiudad!D:D, MATCH(A13, Base_TipoCiudad!A:A, 0)), IF($B$3="C", INDEX(Base_TipoCiudad!E:E, MATCH(A13, Base_TipoCiudad!A:A, 0)), INDEX(Base_TipoCiudad!F:F, MATCH(A13, Base_TipoCiudad!A:A, 0)))))} -> 0.045 | D13: {=INDEX(Arquetipos_Deltas!$C:$O, MATCH($B$4, Arquetipos_Deltas!$A:$A, 0), MATCH("Δ_"&A13, Arquetipos_Deltas!$C$3:$O$3, 0))} -> 0 | E13: =C13+D13 -> 0.045 | G13: =IF(B13="0–1", MAX(0, MIN(1, IF(F13="", E13, F13))), IF(ISNUMBER(SEARCH("meses", B13)), MAX(0, IF(F13="", E13, F13)), IF(F13="", E13, F13))) -> 0.045
A14: horizonte_meses | B14: meses (default si vacío) | C14: {=IF($B$3="A", INDEX(Base_TipoCiudad!C:C, MATCH(A14, Base_TipoCiudad!A:A, 0)), IF($B$3="B", INDEX(Base_TipoCiudad!D:D, MATCH(A14, Base_TipoCiudad!A:A, 0)), IF($B$3="C", INDEX(Base_TipoCiudad!E:E, MATCH(A14, Base_TipoCiudad!A:A, 0)), INDEX(Base_TipoCiudad!F:F, MATCH(A14, Base_TipoCiudad!A:A, 0)))))} -> 24 | D14: {=INDEX(Arquetipos_Deltas!$C:$O, MATCH($B$4, Arquetipos_Deltas!$A:$A, 0), MATCH("Δ_"&A14, Arquetipos_Deltas!$C$3:$O$3, 0))} -> 0 | E14: =C14+D14 -> 24 | F14: {=INDEX(Respuestas!2:2, MATCH("horizonte_meses", Respuestas!1:1, 0))} -> 36 | G14: =IF(B14="0–1", MAX(0, MIN(1, IF(F14="", E14, F14))), IF(ISNUMBER(SEARCH("meses", B14)), MAX(0, IF(F14="", E14, F14)), IF(F14="", E14, F14))) -> 36
A15: costo_m2 | B15: MXN/m² | C15: {=IF($B$3="A", INDEX(Base_TipoCiudad!C:C, MATCH(A15, Base_TipoCiudad!A:A, 0)), IF($B$3="B", INDEX(Base_TipoCiudad!D:D, MATCH(A15, Base_TipoCiudad!A:A, 0)), IF($B$3="C", INDEX(Base_TipoCiudad!E:E, MATCH(A15, Base_TipoCiudad!A:A, 0)), INDEX(Base_TipoCiudad!F:F, MATCH(A15, Base_TipoCiudad!A:A, 0)))))} -> 11000 | D15: {=INDEX(Arquetipos_Deltas!$C:$O, MATCH($B$4, Arquetipos_Deltas!$A:$A, 0), MATCH("Δ_"&A15, Arquetipos_Deltas!$C$3:$O$3, 0))} -> 0 | E15: =C15+D15 -> 11000 | F15: {=INDEX(Respuestas!2:2, MATCH("costo_m2_MXN", Respuestas!1:1, 0))} | G15: =IF(B15="0–1", MAX(0, MIN(1, IF(F15="", E15, F15))), IF(ISNUMBER(SEARCH("meses", B15)), MAX(0, IF(F15="", E15, F15)), IF(F15="", E15, F15))) -> 11000
A16: meses_obra | B16: meses | C16: {=IF($B$3="A", INDEX(Base_TipoCiudad!C:C, MATCH(A16, Base_TipoCiudad!A:A, 0)), IF($B$3="B", INDEX(Base_TipoCiudad!D:D, MATCH(A16, Base_TipoCiudad!A:A, 0)), IF($B$3="C", INDEX(Base_TipoCiudad!E:E, MATCH(A16, Base_TipoCiudad!A:A, 0)), INDEX(Base_TipoCiudad!F:F, MATCH(A16, Base_TipoCiudad!A:A, 0)))))} -> 7 | D16: {=INDEX(Arquetipos_Deltas!$C:$O, MATCH($B$4, Arquetipos_Deltas!$A:$A, 0), MATCH("Δ_"&A16, Arquetipos_Deltas!$C$3:$O$3, 0))} -> 0 | E16: =C16+D16 -> 7 | F16: {=IFERROR(VALUE(SUBSTITUTE(INDEX(Respuestas!2:2, MATCH("meses_obra", Respuestas!1:1, 0)), "+", "")), "")} -> 9 | G16: =IF(B16="0–1", MAX(0, MIN(1, IF(F16="", E16, F16))), IF(ISNUMBER(SEARCH("meses", B16)), MAX(0, IF(F16="", E16, F16)), IF(F16="", E16, F16))) -> 9
A17: permisos_otros_mxn | B17: MXN (licencias, conexiones, imprevistos) | C17: {=IF($B$3="A", INDEX(Base_TipoCiudad!C:C, MATCH(A17, Base_TipoCiudad!A:A, 0)), IF($B$3="B", INDEX(Base_TipoCiudad!D:D, MATCH(A17, Base_TipoCiudad!A:A, 0)), IF($B$3="C", INDEX(Base_TipoCiudad!E:E, MATCH(A17, Base_TipoCiudad!A:A, 0)), INDEX(Base_TipoCiudad!F:F, MATCH(A17, Base_TipoCiudad!A:A, 0)))))} -> 75000 | D17: {=INDEX(Arquetipos_Deltas!$C:$O, MATCH($B$4, Arquetipos_Deltas!$A:$A, 0), MATCH("Δ_"&A17, Arquetipos_Deltas!$C$3:$O$3, 0))} -> 0 | E17: =C17+D17 -> 75000 | G17: =IF(B17="0–1", MAX(0, MIN(1, IF(F17="", E17, F17))), IF(ISNUMBER(SEARCH("meses", B17)), MAX(0, IF(F17="", E17, F17)), IF(F17="", E17, F17))) -> 75000
A18: ocupacion_post | B18: 0–1 | C18: {=IF($B$3="A", INDEX(Base_TipoCiudad!C:C, MATCH(A18, Base_TipoCiudad!A:A, 0)), IF($B$3="B", INDEX(Base_TipoCiudad!D:D, MATCH(A18, Base_TipoCiudad!A:A, 0)), IF($B$3="C", INDEX(Base_TipoCiudad!E:E, MATCH(A18, Base_TipoCiudad!A:A, 0)), INDEX(Base_TipoCiudad!F:F, MATCH(A18, Base_TipoCiudad!A:A, 0)))))} -> 0.88 | D18: {=INDEX(Arquetipos_Deltas!$C:$O, MATCH($B$4, Arquetipos_Deltas!$A:$A, 0), MATCH("Δ_"&A18, Arquetipos_Deltas!$C$3:$O$3, 0))} -> 0 | E18: =C18+D18 -> 0.88 | G18: =IF(B18="0–1", MAX(0, MIN(1, IF(F18="", E18, F18))), IF(ISNUMBER(SEARCH("meses", B18)), MAX(0, IF(F18="", E18, F18)), IF(F18="", E18, F18))) -> 0.88
A19: renta_post_pct_valor_post | B19: % del valor post-obra/mes | C19: {=IF($B$3="A", INDEX(Base_TipoCiudad!C:C, MATCH(A19, Base_TipoCiudad!A:A, 0)), IF($B$3="B", INDEX(Base_TipoCiudad!D:D, MATCH(A19, Base_TipoCiudad!A:A, 0)), IF($B$3="C", INDEX(Base_TipoCiudad!E:E, MATCH(A19, Base_TipoCiudad!A:A, 0)), INDEX(Base_TipoCiudad!F:F, MATCH(A19, Base_TipoCiudad!A:A, 0)))))} -> 0.007 | D19: {=INDEX(Arquetipos_Deltas!$C:$O, MATCH($B$4, Arquetipos_Deltas!$A:$A, 0), MATCH("Δ_"&A19, Arquetipos_Deltas!$C$3:$O$3, 0))} -> 0 | E19: =C19+D19 -> 0.007 | G19: =IF(B19="0–1", MAX(0, MIN(1, IF(F19="", E19, F19))), IF(ISNUMBER(SEARCH("meses", B19)), MAX(0, IF(F19="", E19, F19)), IF(F19="", E19, F19))) -> 0.007
A20: costos_post_pct_valor_post | B20: % del valor post-obra/mes | C20: {=IF($B$3="A", INDEX(Base_TipoCiudad!C:C, MATCH(A20, Base_TipoCiudad!A:A, 0)), IF($B$3="B", INDEX(Base_TipoCiudad!D:D, MATCH(A20, Base_TipoCiudad!A:A, 0)), IF($B$3="C", INDEX(Base_TipoCiudad!E:E, MATCH(A20, Base_TipoCiudad!A:A, 0)), INDEX(Base_TipoCiudad!F:F, MATCH(A20, Base_TipoCiudad!A:A, 0)))))} -> 0.0009 | D20: {=INDEX(Arquetipos_Deltas!$C:$O, MATCH($B$4, Arquetipos_Deltas!$A:$A, 0), MATCH("Δ_"&A20, Arquetipos_Deltas!$C$3:$O$3, 0))} -> 0 | E20: =C20+D20 -> 0.0009 | G20: =IF(B20="0–1", MAX(0, MIN(1, IF(F20="", E20, F20))), IF(ISNUMBER(SEARCH("meses", B20)), MAX(0, IF(F20="", E20, F20)), IF(F20="", E20, F20))) -> 0.0009
A22: gasto_mensual_usado_MXN | B22: MXN/mes | E22: {=IF(ISBLANK(INDEX(Respuestas!2:2, MATCH("gasto_mensual_propiedad_MXN", Respuestas!1:1, 0))), $B$5 * INDEX($G:$G, MATCH("gasto_mensual_pct_valor", $A:$A, 0)), INDEX(Respuestas!2:2, MATCH("gasto_mensual_propiedad_MXN", Respuestas!1:1, 0)))} -> 3500
A23: costos_post_usado_MXN | B23: MXN/mes | E23: {=IF(ISBLANK(INDEX(Respuestas!2:2, MATCH("costos_post_MXN", Respuestas!1:1, 0))), 0, INDEX(Respuestas!2:2, MATCH("costos_post_MXN", Respuestas!1:1, 0)))} -> 0
A24: renta_post_usado_MXN | B24: MXN/mes | E24: {=IF(ISBLANK(INDEX(Respuestas!2:2, MATCH("renta_post_MXN", Respuestas!1:1, 0))), 0, INDEX(Respuestas!2:2, MATCH("renta_post_MXN", Respuestas!1:1, 0)))} -> 0

Sheet Riesgo_Total
A1: Riesgo total (fila 2 de Respuestas)
A3: Suma ponderada | B3: Detalle
A4: {=SUMPRODUCT( N((Respuestas!W2:AE2="Si")+(Respuestas!W2:AE2="Sí")) , TRANSPOSE(Semaforo_Pesos!B4:B12) )} -> 0.4 | B4: Usa 0/1 en columnas de riesgo de 'Respuestas'. Suma esperada 0.00–1.00

Sheet Calculos_Escenarios
A1: Cálculos de escenarios (usa fila 2 de Respuestas + Defaults)
A3: valor_hoy_MXN | B3: {=N( INDEX(Defaults_por_respuesta!$B:$B, MATCH("Valor mercado hoy (MXN)", Defaults_por_respuesta!$A:$A, 0)) )} -> 2000000 | C3: MXN
A4: horizonte_meses | B4: {=N( INDEX(Defaults_por_respuesta!$G:$G, MATCH("horizonte_meses", Defaults_por_respuesta!$A:$A, 0)) )} -> 36 | C4: meses
A5: meses_vender | B5: {=N( INDEX(Defaults_por_respuesta!$G:$G, MATCH("meses_vender", Defaults_por_respuesta!$A:$A, 0)) )} -> 5 | C5: meses
A7: tasa_descuento_anual | B7: {=N( INDEX(Defaults_por_respuesta!$G:$G, MATCH("tasa_descuento_anual", Defaults_por_respuesta!$A:$A, 0)) )} -> 0.19 | C7: %
A8: plusvalia_anual | B8: {=N( INDEX(Defaults_por_respuesta!$G:$G, MATCH("plusvalia_anual", Defaults_por_respuesta!$A:$A, 0)) )} -> 0.045 | C8: %
A9: costos_venta_pct | B9: {=N( INDEX(Defaults_por_respuesta!$G:$G, MATCH("costos_venta_pct", Defaults_por_respuesta!$A:$A, 0)) )} -> 0.07 | C9: %
A10: ocupacion_hoy | B10: {=N( INDEX(Defaults_por_respuesta!$G:$G, MATCH("ocupacion_hoy", Defaults_por_respuesta!$A:$A, 0)) )} -> 0.87 | C10: 0–1
A11: gasto_mensual_MXN | B11: {=N( IF( ISBLANK( INDEX(Defaults_por_respuesta!$F:$F, MATCH("gasto_mensual_usado_MXN", Defaults_por_respuesta!$A:$A, 0)) ), INDEX(Defaults_por_respuesta!$E:$E, MATCH("gasto_mensual_usado_MXN", Defaults_por_respuesta!$A:$A, 0)), INDEX(Defaults_por_respuesta!$F:$F, MATCH("gasto_mensual_usado_MXN", Defaults_por_respuesta!$A:$A, 0)) ) )} -> 3500 | C11: MXN/mes
A12: renta_hoy_pct_valor | B12: {=IFERROR( IF( N(INDEX(Respuestas!A:ZZ, MAX(FILTRAR(ROW(Respuestas!A:A), Respuestas!A:A<>"")), MATCH("renta_mensual_actual", Respuestas!1:1, 0)))>0, N(INDEX(Respuestas!A:ZZ, MAX(FILTRAR(ROW(Respuestas!A:A), Respuestas!A:A<>"")), MATCH("renta_mensual_actual", Respuestas!1:1, 0))) / N($B$4), N( INDEX(Defaults_por_respuesta!$G:$G, MATCH("renta_hoy_pct_valor", Defaults_por_respuesta!$A:$A, 0)) ) ), 0 )} -> 0 | C12: % del valor/mes
A13: renta_hoy_MXN | B13: {=IFERROR( IF( N(INDEX(Respuestas!A:ZZ, MAX(FILTRAR(ROW(Respuestas!A:A), Respuestas!A:A<>"")), MATCH("renta_mensual_actual", Respuestas!1:1, 0)))>0, N(INDEX(Respuestas!A:ZZ, MAX(FILTRAR(ROW(Respuestas!A:A), Respuestas!A:A<>"")), MATCH("renta_mensual_actual", Respuestas!1:1, 0))), N($B$4 * $B$12) ), N($B$4 * $B$12) )} -> 0 | C13: MXN/mes
A15: m2_construccion | B15: {=IFERROR( N(INDEX(Respuestas!A:ZZ, MAX(FILTRAR(ROW(Respuestas!A:A), Respuestas!A:A<>"")), MATCH("m2_construccion", Respuestas!1:1, 0))), 0 )} -> 0 | C15: m²
A16: costo_m2 | B16: {=N( INDEX(Defaults_por_respuesta!$G:$G, MATCH("costo_m2", Defaults_por_respuesta!$A:$A, 0)) )} -> 11000 | C16: MXN/m²
A17: permisos_MXN | B17: {=N( INDEX(Defaults_por_respuesta!$G:$G, MATCH("permisos_otros_mxn", Defaults_por_respuesta!$A:$A, 0)) )} -> 75000 | C17: MXN
A18: capex_total_MXN | B18: =N(B15)*N(B16) + N(B17) -> 75000 | C18: MXN
A19: meses_obra | B19: {=N( INDEX(Defaults_por_respuesta!$G:$G, MATCH("meses_obra", Defaults_por_respuesta!$A:$A, 0)) )} -> 9 | C19: meses
A20: ocupacion_post | B20: {=N( INDEX(Defaults_por_respuesta!$G:$G, MATCH("ocupacion_post", Defaults_por_respuesta!$A:$A, 0)) )} -> 0.88 | C20: 0–1
A21: renta_post_pct_valor_post | B21: {=N( INDEX(Defaults_por_respuesta!$G:$G, MATCH("renta_post_pct_valor_post", Defaults_por_respuesta!$A:$A, 0)) )} -> 0.007 | C21: % del valor/mes
A22: costos_post_pct_valor_post | B22: {=N( INDEX(Defaults_por_respuesta!$G:$G, MATCH("costos_post_pct_valor_post", Defaults_por_respuesta!$A:$A, 0)) )} -> 0.0009 | C22: % del valor/mes
A23: valor_post_obra_MXN | B23: =N(B3) + N(B18) -> 2075000 | C23: MXN
A24: renta_post_usado_MXN | B24: {=N( IF( NOT(ISBLANK( INDEX(Defaults_por_respuesta!$F:$F, MATCH("renta_post_usado_MXN", Defaults_por_respuesta!$A:$A, 0)) )), INDEX(Defaults_por_respuesta!$F:$F, MATCH("renta_post_usado_MXN", Defaults_por_respuesta!$A:$A, 0)), IF( NOT(ISBLANK( INDEX(Defaults_por_respuesta!$E:$E, MATCH("renta_post_usado_MXN", Defaults_por_respuesta!$A:$A, 0)) )), INDEX(Defaults_por_respuesta!$E:$E, MATCH("renta_post_usado_MXN", Defaults_por_respuesta!$A:$A, 0)), B23 * B21 ) ) )} -> 0 | C24: MXN/mes
A25: costos_post_usado_MXN | B25: {=N( IF( NOT(ISBLANK( INDEX(Defaults_por_respuesta!$F:$F, MATCH("costos_post_usado_MXN", Defaults_por_respuesta!$A:$A, 0)) )), INDEX(Defaults_por_respuesta!$F:$F, MATCH("costos_post_usado_MXN", Defaults_por_respuesta!$A:$A, 0)), IF( NOT(ISBLANK( INDEX(Defaults_por_respuesta!$E:$E, MATCH("costos_post_usado_MXN", Defaults_por_respuesta!$A:$A, 0)) )), INDEX(Defaults_por_respuesta!$E:$E, MATCH("costos_post_usado_MXN", Defaults_por_respuesta!$A:$A, 0)), B23 * B22 ) ) )} -> 0 | C25: MXN/mes
A27: tasa_mensual | B27: =POWER(1 + B7, 1/12) - 1 -> 0.014601687 | C27: %
A28: g_mensual_plusvalia | B28: =POWER(1 + B8, 1/12) - 1 -> 0.0036748094 | C28: %
A29: n_renta_sin_obra | B29: =N(B4) -> 36 | C29: meses
A30: n_post_obra | B30: =MAX(0, N(B4) - N(B19)) -> 27 | C30: meses
A32: Escenario | B32: NPV (MXN)
A33: Vender ahora | B33: =$B$3*(1-B9)/POWER(1+B27, B5) -> 1729955.9 | C33: MXN
A34: Rentar (sin obra) | B34: =N( ( (B13 * B10 - B11) * IF(B26>0, (1 - POWER(1 + B26, -B29)) / B26, B29) ) + ( (B3 * POWER(1 + B27, B29)) * (1 - B9) / POWER(1 + B26, B29 + B5) ) ) -> 3008395.7 | C34: MXN
A35: Construir & vender | B35: =N( -B18 + ( B23 * (1 - B9) ) / POWER(1 + B26, B19 + B5) ) -> 1854750 | C35: MXN
A36: Construir & rentar | B36: =N( -B18 + ( (B24 * B20 - B25) * IF(B26>0, (1 - POWER(1 + B26, -B30)) / B26, B30) ) + ( (B23 * POWER(1 + B27, B30)) * (1 - B9) / POWER(1 + B26, B30 + B5) ) ) -> 2779182.3 | C36: MXN
A37: Esperar | B37: =N( ( -B11 * IF(B26>0, (1 - POWER(1 + B26, -B29)) / B26, B29) ) + ( (B3 * POWER(1 + B27, B29)) * (1 - B9) / POWER(1 + B26, B29 + B5) ) ) -> 3008395.7 | C37: MXN

Sheet s_Info
A3: ultims fila | B3: =MAX(FILTRAR(ROW(Respuestas!A:A), Respuestas!A:A<>"")) -> #NAME?

Sheet Reporte_1Pager_Data
A1: Resumen para 1-pager
A3: Escenario | B3: NPV (MXN) | C3: Notas
A4: Vender ahora | B4: {=IFERROR(INDEX(Calculos_Escenarios!B:B, MATCH("Vender ahora", Calculos_Escenarios!A:A, 0)), "")} -> 1729955.9 | C4: {=IF(ISNUMBER(B4), "Vendes en " & N(INDEX(Calculos_Escenarios!B:B, MATCH("meses_vender", Calculos_Escenarios!A:A, 0))) & " m; costos " & TEXT(N(INDEX(Calculos_Escenarios!B:B, MATCH("costos_venta_pct", Calculos_Escenarios!A:A, 0))), "0%"), "" )} -> Vendes en 5 m; costos 7%
A5: Rentar (sin obra) | B5: {=IFERROR(INDEX(Calculos_Escenarios!B:B, MATCH("Rentar (sin obra)", Calculos_Escenarios!A:A, 0)), "")} -> 3008395.7 | C5: {=IF(ISNUMBER(B5), "Rentas " & N(INDEX(Calculos_Escenarios!B:B, MATCH("n_renta_sin_obra", Calculos_Escenarios!A:A, 0))) & " m; neto=" & TEXT( N(INDEX(Calculos_Escenarios!B:B, MATCH("renta_hoy_MXN", Calculos_Escenarios!A:A, 0))) - N(INDEX(Calculos_Escenarios!B:B, MATCH("gasto_mensual_MXN", Calculos_Escenarios!A:A, 0))), "$#,##0" ) & "/mes; vendes en " & ( N(INDEX(Calculos_Escenarios!B:B, MATCH("n_renta_sin_obra", Calculos_Escenarios!A:A, 0))) + N(INDEX(Calculos_Escenarios!B:B, MATCH("meses_vender", Calculos_Escenarios!A:A, 0))) ) & " m", "" )} -> Rentas 36 m; neto=-$3.500/mes; vendes en 41 m
A6: Construir & vender | B6: {=IFERROR(INDEX(Calculos_Escenarios!B:B, MATCH("Construir & vender", Calculos_Escenarios!A:A, 0)), "")} -> 1854750 | C6: {=IF(ISNUMBER(B6), "Capex " & TEXT(N(INDEX(Calculos_Escenarios!B:B, MATCH("capex_total_MXN", Calculos_Escenarios!A:A, 0))), "$#,##0") & "; obra " & N(INDEX(Calculos_Escenarios!B:B, MATCH("meses_obra", Calculos_Escenarios!A:A, 0))) & " m", "" )} -> Capex $75.000; obra 9 m
A7: Construir & rentar | B7: {=IFERROR(INDEX(Calculos_Escenarios!B:B, MATCH("Construir & rentar", Calculos_Escenarios!A:A, 0)), "")} -> 2779182.3 | C7: {=IF(ISNUMBER(B7), "Capex " & TEXT(N(INDEX(Calculos_Escenarios!B:B, MATCH("capex_total_MXN", Calculos_Escenarios!A:A, 0))), "$#,##0") & "; renta " & N(INDEX(Calculos_Escenarios!B:B, MATCH("n_post_obra", Calculos_Escenarios!A:A, 0))) & " m; ocup " & TEXT(N(INDEX(Calculos_Escenarios!B:B, MATCH("ocupacion_post", Calculos_Escenarios!A:A, 0))), "0%"), "" )} -> Capex $75.000; renta 27 m; ocup 88%
A8: Esperar | B8: {=IFERROR(INDEX(Calculos_Escenarios!B:B, MATCH("Esperar", Calculos_Escenarios!A:A, 0)), "")} -> 3008395.7 | C8: {=IF(ISNUMBER(B8), "Mantener " & N(INDEX(Calculos_Escenarios!B:B, MATCH("n_renta_sin_obra", Calculos_Escenarios!A:A, 0))) & " m; gasto " & TEXT(N(INDEX(Calculos_Escenarios!B:B, MATCH("gasto_mensual_MXN", Calculos_Escenarios!A:A, 0))), "$#,##0") & "/mes", "" )} -> Mantener 36 m; gasto $3.500/mes
A10: Rank
A11: Vender ahora | B11: =IF(ISNUMBER(B4), 1+COUNTIF($B$4:$B$8, ">"&B4), "") -> 5
A12: Rentar (sin obra) | B12: =IF(ISNUMBER(B5), 1+COUNTIF($B$4:$B$8, ">"&B5), "") -> 1
A13: Construir & vender | B13: =IF(ISNUMBER(B6), 1+COUNTIF($B$4:$B$8, ">"&B6), "") -> 4
A14: Construir & rentar | B14: =IF(ISNUMBER(B7), 1+COUNTIF($B$4:$B$8, ">"&B7), "") -> 3
A15: Esperar | B15: =IF(ISNUMBER(B8), 1+COUNTIF($B$4:$B$8, ">"&B8), "") -> 1
A17: Ganador | B17: {=IF(COUNT($B$4:$B$8)=0, "", INDEX($A$4:$A$8, MATCH(MAX(IF(ISNUMBER($B$4:$B$8), $B$4:$B$8)), $B$4:$B$8, 0)))} -> Rentar (sin obra)
A18: NPV ganador (MXN) | B18: =IF(COUNT($B$4:$B$8)=0, "", MAX($B$4:$B$8)) -> 3008395.7
A19: Segundo lugar (NPV) | B19: =IF(COUNT($B$4:$B$8)<2, "", LARGE($B$4:$B$8, 2)) -> 3008395.7
A20: Ventaja % vs 2º | B20: =IF(OR(B18="", B19="", B19=0), "", (B18-B19)/ABS(B19)) -> 0
A22: Riesgo total (0–1) | B22: =IFERROR(Riesgo_Total!$A$4, "") -> 0.4
A24: Recomendación final | B24: =IF(B17="", "", IF(AND(ISNUMBER(B22), B22>=0.6, OR(B17="Construir & vender", B17="Construir & rentar")), B17&" (alto riesgo: valida permisos/mercado)", B17)) -> Rentar (sin obra)
A25: Nota explicativa | B25: =IF(B17="", "", "Ganador: "&B17&". NPV: "&TEXT(B18, "$#,##0")&". Ventaja vs 2º: "&IF(ISNUMBER(B20), TEXT(B20, "0,0%"), "n/a")&". Riesgo: "&IF(ISNUMBER(B22), TEXT(B22, "0,0%"), "n/a")&".") -> Ganador: Rentar (sin obra). NPV: $3.008.396. Ventaja vs 2º: 00%. Riesgo: 40%.
